setup.py
weather_by_3hour/__init__.py
weather_by_3hour/weather_by_3hour.py
weather_by_3hour.egg-info/PKG-INFO
weather_by_3hour.egg-info/SOURCES.txt
weather_by_3hour.egg-info/dependency_links.txt
weather_by_3hour.egg-info/requires.txt
weather_by_3hour.egg-info/top_level.txt