Metadata-Version: 1.1
Name: weather-by-3hour
Version: 1.0.0
Summary: Weather forecast data
Home-page: https://github.com/c-ernest/packages.git
Author: Ernest Chukwunta
Author-email: yourmail@example.com
License: MIT
Keywords: weather,forecast,openweather
Platform: UNKNOWN
Classifier: Intended Audience :: Developers
Classifier: Topic :: Software Development :: Build Tools
Classifier: License :: OSI Approved :: MIT License
Classifier: Programming Language :: Python :: 3.7
